binprice/__init__.py
binprice/prices.py
binprice-0.0.3.dist-info/LICENSE
binprice-0.0.3.dist-info/METADATA
binprice-0.0.3.dist-info/WHEEL
binprice-0.0.3.dist-info/top_level.txt
binprice-0.0.3.dist-info/RECORD
