Metadata-Version: 2.1
Name: binprice
Version: 0.0.3
Classifier: Programming Language :: Python :: 3
Classifier: License :: OSI Approved :: MIT License
Requires-Python: >=3.7
License-File: LICENSE
Requires-Dist: requests (==2.28.1)
Requires-Dist: matplotlib (==3.5.3)
Requires-Dist: pandas (==1.3.5)
Requires-Dist: colorama (==0.4.6)
